{"0":{"channel":"<#407766972798074880>","active":true,"question":"This is Question","answers":{"1":"AnswerA","2":"B Test","3":"Cd sd a","4":"5f fd"}},"1":{"channel":"<#407766972798074880>","active":true,"question":"This is Question","answers":{"1":"AnswerA","2":"B Test","3":"Cd sd a","4":"5f fd"}},"2":{"channel":"<#407766972798074880>","active":true,"question":"This is Question","answers":{"1":"AnswerA","2":"B Test","3":"Cd sd a","4":"5f fd"}},"3":{"channel":"<#407766972798074880>","active":true,"question":"This is Question","answers":{"1":"AnswerA","2":"B Test","3":"Cd sd a","4":"5f fd"}},"4":{"channel":"<#407766972798074880>","active":true,"question":"This is Question","answers":{"1":"AnswerA","2":"B Test","3":"Cd sd a","4":"5f fd"}},"5":{"channel":"<#407766972798074880>","active":true,"question":"This is Question","answers":{"1":"AnswerA","2":"B Test","3":"Cd sd a","4":"5f fd"}},"6": {"channel": "<#407766972798074880>", "active": true, "question": "This is Question", "answers": {"1": "AnswerA","2": "B Test","3": "Cd sd a","4": "5f fd"}}}